mangadlmao/__init__.py
mangadlmao/cbz.py
mangadlmao/mangadlmao.py
mangadlmao/utils.py
mangadlmao/apis/__init__.py
mangadlmao/apis/mangadex.py
mangadlmao/apis/mangaplus.py
mangadlmao/apis/weebcentral.py
mangadlmao-1.5.3.dist-info/licenses/LICENSE
mangadlmao-1.5.3.dist-info/METADATA
mangadlmao-1.5.3.dist-info/WHEEL
mangadlmao-1.5.3.dist-info/entry_points.txt
mangadlmao-1.5.3.dist-info/top_level.txt
mangadlmao-1.5.3.dist-info/RECORD
