Metadata-Version: 2.4
Name: mangadlmao
Version: 1.5.3
Summary: A cli script to download and package manga into CBZ for Komga
Home-page: https://github.com/lmaonator/mangadlmao
Author: lmaonator
Author-email: lmaonator@gmail.com
Project-URL: Bug Tracker, https://github.com/lmaonator/mangadlmao/issues
Classifier: Development Status :: 4 - Beta
Classifier: Environment :: Console
Classifier: License :: OSI Approved :: GNU General Public License v3 (GPLv3)
Classifier: Natural Language :: English
Classifier: Operating System :: OS Independent
Classifier: Programming Language :: Python :: 3.9
Classifier: Topic :: Internet :: WWW/HTTP
Classifier: Topic :: Multimedia :: Graphics
Classifier: Topic :: Utilities
Requires-Python: >=3.9
License-File: LICENSE
Requires-Dist: requests
Requires-Dist: appdirs
Requires-Dist: PyYAML
Requires-Dist: click
Requires-Dist: beautifulsoup4
Requires-Dist: filetype
Dynamic: license-file
